ca_certificates/__init__.py
gradio_videotimeline-0.0.0.dist-info/METADATA
gradio_videotimeline-0.0.0.dist-info/WHEEL
gradio_videotimeline-0.0.0.dist-info/top_level.txt
gradio_videotimeline-0.0.0.dist-info/RECORD
