Metadata-Version: 2.4
Name: gradio_videotimeline
Version: 0.0.0
Summary: Dummy gradio_videotimeline package for PyPI
Author-email: Your Name <you@example.com>
Requires-Python: >=3.7
